{
  "creator": "ou_8554528ee6e965bad56710acde1c7847",
  "has_child": false,
  "node_create_time": "1698146477",
  "node_token": "KHAMwm0HUiU6qdkH2LOcu0FFnug",
  "node_type": "origin",
  "obj_create_time": "1698146477",
  "obj_edit_time": "1703644483",
  "obj_token": "HE1DdqSMWoslMCx5jiLc9mqTn0g",
  "obj_type": "docx",
  "origin_node_token": "KHAMwm0HUiU6qdkH2LOcu0FFnug",
  "origin_space_id": "7167193056431783939",
  "owner": "ou_8554528ee6e965bad56710acde1c7847",
  "parent_node_token": "XiOsw8A3eibZInk1aJNceBqznLb",
  "space_id": "7167193056431783939",
  "title": "MFA",
  "slug": "multi-factor-auth",
  "blocks": {
    "items": [
      {
        "block_id": "HE1DdqSMWoslMCx5jiLc9mqTn0g",
        "block_type": 1,
        "children": [
          "IMGbdefy6o6WgQxDksoc9iQLn3b",
          "Kwehd5TA7oMD1QxJKgCcuZ1mnAg",
          "SArEdjqpPoqBojxBt2hccPLCntg",
          "UtCSdMHXUoMdSKxsBtncPe2Pnqf",
          "SaySdGrhhoWHFBx28eNcQ2Tmnyc",
          "EDHLdshisok3YUxZ2M4cqaKon2b",
          "O5SadXGIboHDEzxgrklcGlConMd",
          "HHaTd7WO8o65IPxej7gc8EednBh",
          "ZN8kdVJtGov1f8xBYUYc3ChGncg",
          "EFLCdZhDdoOp8qx48rmcLG8RnXg",
          "JipQdkVLuoaxFMxm8PrcutOVnYg",
          "CRgVd6Y7dohMnHxi6dTc3ogbnme",
          "Mvbad66r1oSfDxxCaAYcJJndn2e",
          "Jnv6dAetLodfogxyzcYc2maIn76",
          "K35CdZJaYo2YqMxjpsTcy937nfe",
          "QqmGd3jVxowHHjxzps3cH6CLnSc",
          "QCf5dTsFKoDYqQxQsr9cr0xVnAc"
        ],
        "page": {
          "elements": [
            {
              "text_run": {
                "content": "MFA",
                "text_element_style": {
                  "bold": false,
                  "inline_code": false,
                  "italic": false,
                  "strikethrough": false,
                  "underline": false
                }
              }
            }
          ],
          "style": {
            "align": 1
          }
        },
        "parent_id": ""
      },
      {
        "block_id": "IMGbdefy6o6WgQxDksoc9iQLn3b",
        "block_type": 2,
        "parent_id": "HE1DdqSMWoslMCx5jiLc9mqTn0g",
        "text": {
          "elements": [
            {
              "text_run": {
                "content": "Authentication serves as a gateway to verify one's identity during the login process. Zilliz Cloud enhances this security by offering Multi-factor Authentication (MFA), an advanced login method requiring additional verification beyond a password. MFA is an effective measure against unauthorized access and is recommended for all users. Currently, only users registered with a work email and password can manage MFA on the web console. With MFA enabled, you must enter both your password and the email verification code during each login attempt for added security.",
                "text_element_style": {
                  "bold": false,
                  "inline_code": false,
                  "italic": false,
                  "strikethrough": false,
                  "underline": false
                }
              }
            }
          ],
          "style": {
            "align": 1,
            "folded": false
          }
        }
      },
      {
        "block_id": "Kwehd5TA7oMD1QxJKgCcuZ1mnAg",
        "block_type": 5,
        "heading3": {
          "elements": [
            {
              "text_run": {
                "content": "Enable MFA",
                "text_element_style": {
                  "bold": false,
                  "inline_code": false,
                  "italic": false,
                  "strikethrough": false,
                  "underline": false
                }
              }
            }
          ],
          "style": {
            "align": 1,
            "folded": false
          }
        },
        "parent_id": "HE1DdqSMWoslMCx5jiLc9mqTn0g"
      },
      {
        "block_id": "SArEdjqpPoqBojxBt2hccPLCntg",
        "block_type": 13,
        "ordered": {
          "elements": [
            {
              "text_run": {
                "content": "Go to your ",
                "text_element_style": {
                  "bold": false,
                  "inline_code": false,
                  "italic": false,
                  "strikethrough": false,
                  "underline": false
                }
              }
            },
            {
              "text_run": {
                "content": "Profile",
                "text_element_style": {
                  "bold": true,
                  "inline_code": false,
                  "italic": false,
                  "strikethrough": false,
                  "underline": false
                }
              }
            },
            {
              "text_run": {
                "content": " and choose ",
                "text_element_style": {
                  "bold": false,
                  "inline_code": false,
                  "italic": false,
                  "strikethrough": false,
                  "underline": false
                }
              }
            },
            {
              "text_run": {
                "content": "Account Settings",
                "text_element_style": {
                  "bold": true,
                  "inline_code": false,
                  "italic": false,
                  "strikethrough": false,
                  "underline": false
                }
              }
            },
            {
              "text_run": {
                "content": ".",
                "text_element_style": {
                  "bold": false,
                  "inline_code": false,
                  "italic": false,
                  "strikethrough": false,
                  "underline": false
                }
              }
            }
          ],
          "style": {
            "align": 1,
            "folded": false,
            "indentation_level": "NoIndent"
          }
        },
        "parent_id": "HE1DdqSMWoslMCx5jiLc9mqTn0g"
      },
      {
        "block_id": "UtCSdMHXUoMdSKxsBtncPe2Pnqf",
        "block_type": 13,
        "ordered": {
          "elements": [
            {
              "text_run": {
                "content": "Activate the Multi-Factor Authentication toggle.",
                "text_element_style": {
                  "bold": false,
                  "inline_code": false,
                  "italic": false,
                  "strikethrough": false,
                  "underline": false
                }
              }
            }
          ],
          "style": {
            "align": 1,
            "folded": false
          }
        },
        "parent_id": "HE1DdqSMWoslMCx5jiLc9mqTn0g"
      },
      {
        "block_id": "SaySdGrhhoWHFBx28eNcQ2Tmnyc",
        "block_type": 13,
        "ordered": {
          "elements": [
            {
              "text_run": {
                "content": "In the dialog box, confirm by entering your account password.",
                "text_element_style": {
                  "bold": false,
                  "inline_code": false,
                  "italic": false,
                  "strikethrough": false,
                  "underline": false
                }
              }
            }
          ],
          "style": {
            "align": 1,
            "folded": false
          }
        },
        "parent_id": "HE1DdqSMWoslMCx5jiLc9mqTn0g"
      },
      {
        "block_id": "EDHLdshisok3YUxZ2M4cqaKon2b",
        "block_type": 13,
        "ordered": {
          "elements": [
            {
              "text_run": {
                "content": "Enter the verification code sent to your registered email to verify your identity.",
                "text_element_style": {
                  "bold": false,
                  "inline_code": false,
                  "italic": false,
                  "strikethrough": false,
                  "underline": false
                }
              }
            }
          ],
          "style": {
            "align": 1,
            "folded": false
          }
        },
        "parent_id": "HE1DdqSMWoslMCx5jiLc9mqTn0g"
      },
      {
        "block_id": "O5SadXGIboHDEzxgrklcGlConMd",
        "block_type": 13,
        "ordered": {
          "elements": [
            {
              "text_run": {
                "content": "You will be redirected to the login page. A prompt will appear notifying you that MFA is successfully enabled.",
                "text_element_style": {
                  "bold": false,
                  "inline_code": false,
                  "italic": false,
                  "strikethrough": false,
                  "underline": false
                }
              }
            }
          ],
          "style": {
            "align": 1,
            "folded": false
          }
        },
        "parent_id": "HE1DdqSMWoslMCx5jiLc9mqTn0g"
      },
      {
        "block_id": "HHaTd7WO8o65IPxej7gc8EednBh",
        "block_type": 34,
        "children": [
          "Wn8RdPjnvoVLgLxRNQDcUd2Hn0e",
          "T5O2dmuaMoe0L1x8PYBcZn38nBc",
          "Mka3dclB1o6qDbx3INFcswo9nC5"
        ],
        "parent_id": "HE1DdqSMWoslMCx5jiLc9mqTn0g",
        "quote_container": {}
      },
      {
        "block_id": "Wn8RdPjnvoVLgLxRNQDcUd2Hn0e",
        "block_type": 2,
        "parent_id": "HHaTd7WO8o65IPxej7gc8EednBh",
        "text": {
          "elements": [
            {
              "text_run": {
                "content": "📘 Notes",
                "text_element_style": {
                  "bold": false,
                  "inline_code": false,
                  "italic": false,
                  "strikethrough": false,
                  "underline": false
                }
              }
            }
          ],
          "style": {
            "align": 1,
            "folded": false
          }
        }
      },
      {
        "block_id": "T5O2dmuaMoe0L1x8PYBcZn38nBc",
        "block_type": 2,
        "parent_id": "HHaTd7WO8o65IPxej7gc8EednBh",
        "text": {
          "elements": [
            {
              "text_run": {
                "content": "Users with accounts linked to Google are subject to Google's own MFA settings. For more information, see ",
                "text_element_style": {
                  "bold": false,
                  "inline_code": false,
                  "italic": false,
                  "strikethrough": false,
                  "underline": false
                }
              }
            },
            {
              "text_run": {
                "content": "Turn on 2-Step Verification",
                "text_element_style": {
                  "bold": false,
                  "inline_code": false,
                  "italic": false,
                  "link": {
                    "url": "https%3A%2F%2Fsupport.google.com%2Faccounts%2Fanswer%2F185839%3Fhl%3Den%26ref_topic%3D7189195%26sjid%3D2449417013251062800-AP"
                  },
                  "strikethrough": false,
                  "underline": false
                }
              }
            },
            {
              "text_run": {
                "content": ". ",
                "text_element_style": {
                  "bold": false,
                  "inline_code": false,
                  "italic": false,
                  "strikethrough": false,
                  "underline": false
                }
              }
            }
          ],
          "style": {
            "align": 1,
            "folded": false
          }
        }
      },
      {
        "block_id": "Mka3dclB1o6qDbx3INFcswo9nC5",
        "block_type": 2,
        "parent_id": "HHaTd7WO8o65IPxej7gc8EednBh",
        "text": {
          "elements": [
            {
              "text_run": {
                "content": "Similarly, MFA settings for GitHub-linked accounts are managed by GitHub. For more information, see ",
                "text_element_style": {
                  "bold": false,
                  "inline_code": false,
                  "italic": false,
                  "strikethrough": false,
                  "underline": false
                }
              }
            },
            {
              "text_run": {
                "content": "Configuring two-factor authentication",
                "text_element_style": {
                  "bold": false,
                  "inline_code": false,
                  "italic": false,
                  "link": {
                    "url": "https%3A%2F%2Fdocs.github.com%2Fen%2Fauthentication%2Fsecuring-your-account-with-two-factor-authentication-2fa%2Fconfiguring-two-factor-authentication"
                  },
                  "strikethrough": false,
                  "underline": false
                }
              }
            },
            {
              "text_run": {
                "content": ".",
                "text_element_style": {
                  "bold": false,
                  "inline_code": false,
                  "italic": false,
                  "strikethrough": false,
                  "underline": false
                }
              }
            }
          ],
          "style": {
            "align": 1,
            "folded": false
          }
        }
      },
      {
        "block_id": "ZN8kdVJtGov1f8xBYUYc3ChGncg",
        "block_type": 26,
        "iframe": {
          "component": {
            "iframe_type": 8,
            "url": "https%3A%2F%2Fwww.figma.com%2Ffile%2FRb9z8tsmYYdqdultiKx7kT%2FZilliz-Diagrams%3Ftype%3Ddesign%26node-id%3D17042-488%26mode%3Ddesign%26t%3DH1TA3QUFdIqvLTC9-4"
          }
        },
        "parent_id": "HE1DdqSMWoslMCx5jiLc9mqTn0g"
      },
      {
        "block_id": "EFLCdZhDdoOp8qx48rmcLG8RnXg",
        "block_type": 5,
        "heading3": {
          "elements": [
            {
              "text_run": {
                "content": "Disable MFA",
                "text_element_style": {
                  "bold": false,
                  "inline_code": false,
                  "italic": false,
                  "strikethrough": false,
                  "underline": false
                }
              }
            }
          ],
          "style": {
            "align": 1,
            "folded": false
          }
        },
        "parent_id": "HE1DdqSMWoslMCx5jiLc9mqTn0g"
      },
      {
        "block_id": "JipQdkVLuoaxFMxm8PrcutOVnYg",
        "block_type": 13,
        "ordered": {
          "elements": [
            {
              "text_run": {
                "content": "Go to your ",
                "text_element_style": {
                  "bold": false,
                  "inline_code": false,
                  "italic": false,
                  "strikethrough": false,
                  "underline": false
                }
              }
            },
            {
              "text_run": {
                "content": "Profile",
                "text_element_style": {
                  "bold": true,
                  "inline_code": false,
                  "italic": false,
                  "strikethrough": false,
                  "underline": false
                }
              }
            },
            {
              "text_run": {
                "content": " and choose ",
                "text_element_style": {
                  "bold": false,
                  "inline_code": false,
                  "italic": false,
                  "strikethrough": false,
                  "underline": false
                }
              }
            },
            {
              "text_run": {
                "content": "Account Settings",
                "text_element_style": {
                  "bold": true,
                  "inline_code": false,
                  "italic": false,
                  "strikethrough": false,
                  "underline": false
                }
              }
            },
            {
              "text_run": {
                "content": ".",
                "text_element_style": {
                  "bold": false,
                  "inline_code": false,
                  "italic": false,
                  "strikethrough": false,
                  "underline": false
                }
              }
            }
          ],
          "style": {
            "align": 1,
            "folded": false
          }
        },
        "parent_id": "HE1DdqSMWoslMCx5jiLc9mqTn0g"
      },
      {
        "block_id": "CRgVd6Y7dohMnHxi6dTc3ogbnme",
        "block_type": 13,
        "ordered": {
          "elements": [
            {
              "text_run": {
                "content": "Deactivate the Multi-Factor Authentication toggle.",
                "text_element_style": {
                  "bold": false,
                  "inline_code": false,
                  "italic": false,
                  "strikethrough": false,
                  "underline": false
                }
              }
            }
          ],
          "style": {
            "align": 1,
            "folded": false
          }
        },
        "parent_id": "HE1DdqSMWoslMCx5jiLc9mqTn0g"
      },
      {
        "block_id": "Mvbad66r1oSfDxxCaAYcJJndn2e",
        "block_type": 13,
        "ordered": {
          "elements": [
            {
              "text_run": {
                "content": "In the dialog box, click ",
                "text_element_style": {
                  "bold": false,
                  "inline_code": false,
                  "italic": false,
                  "strikethrough": false,
                  "underline": false
                }
              }
            },
            {
              "text_run": {
                "content": "Disable",
                "text_element_style": {
                  "bold": true,
                  "inline_code": false,
                  "italic": false,
                  "strikethrough": false,
                  "underline": false
                }
              }
            },
            {
              "text_run": {
                "content": " to confirm your action.",
                "text_element_style": {
                  "bold": false,
                  "inline_code": false,
                  "italic": false,
                  "strikethrough": false,
                  "underline": false
                }
              }
            }
          ],
          "style": {
            "align": 1,
            "folded": false
          }
        },
        "parent_id": "HE1DdqSMWoslMCx5jiLc9mqTn0g"
      },
      {
        "block_id": "Jnv6dAetLodfogxyzcYc2maIn76",
        "block_type": 13,
        "ordered": {
          "elements": [
            {
              "text_run": {
                "content": "Verify your identity by entering the verification code sent to your email address. Click ",
                "text_element_style": {
                  "bold": false,
                  "inline_code": false,
                  "italic": false,
                  "strikethrough": false,
                  "underline": false
                }
              }
            },
            {
              "text_run": {
                "content": "Disable",
                "text_element_style": {
                  "bold": true,
                  "inline_code": false,
                  "italic": false,
                  "strikethrough": false,
                  "underline": false
                }
              }
            },
            {
              "text_run": {
                "content": ".",
                "text_element_style": {
                  "bold": false,
                  "inline_code": false,
                  "italic": false,
                  "strikethrough": false,
                  "underline": false
                }
              }
            }
          ],
          "style": {
            "align": 1,
            "folded": false
          }
        },
        "parent_id": "HE1DdqSMWoslMCx5jiLc9mqTn0g"
      },
      {
        "block_id": "K35CdZJaYo2YqMxjpsTcy937nfe",
        "block_type": 13,
        "ordered": {
          "elements": [
            {
              "text_run": {
                "content": "A prompt will appear notifying you that MFA is successfully disabled.",
                "text_element_style": {
                  "bold": false,
                  "inline_code": false,
                  "italic": false,
                  "strikethrough": false,
                  "underline": false
                }
              }
            }
          ],
          "style": {
            "align": 1,
            "folded": false
          }
        },
        "parent_id": "HE1DdqSMWoslMCx5jiLc9mqTn0g"
      },
      {
        "block_id": "QqmGd3jVxowHHjxzps3cH6CLnSc",
        "block_type": 34,
        "children": [
          "MpPhd3mu4o73HjxktQscC6z3nge",
          "VEZodITy1onHGDxGpLMcnlphnsh",
          "F1OtdKdztomsiqxt242cJCVUnce"
        ],
        "parent_id": "HE1DdqSMWoslMCx5jiLc9mqTn0g",
        "quote_container": {}
      },
      {
        "block_id": "MpPhd3mu4o73HjxktQscC6z3nge",
        "block_type": 2,
        "parent_id": "QqmGd3jVxowHHjxzps3cH6CLnSc",
        "text": {
          "elements": [
            {
              "text_run": {
                "content": "📘 Notes",
                "text_element_style": {
                  "bold": false,
                  "inline_code": false,
                  "italic": false,
                  "strikethrough": false,
                  "underline": false
                }
              }
            }
          ],
          "style": {
            "align": 1,
            "folded": false
          }
        }
      },
      {
        "block_id": "VEZodITy1onHGDxGpLMcnlphnsh",
        "block_type": 2,
        "parent_id": "QqmGd3jVxowHHjxzps3cH6CLnSc",
        "text": {
          "elements": [
            {
              "text_run": {
                "content": "Users with accounts linked to Google are subject to Google's own MFA settings. For more information, see  ",
                "text_element_style": {
                  "bold": false,
                  "inline_code": false,
                  "italic": false,
                  "strikethrough": false,
                  "underline": false
                }
              }
            },
            {
              "text_run": {
                "content": "Turn off 2-Step Verification",
                "text_element_style": {
                  "bold": false,
                  "inline_code": false,
                  "italic": false,
                  "link": {
                    "url": "https%3A%2F%2Fsupport.google.com%2Faccounts%2Fanswer%2F1064203%3Fhl%3Den%26ref_topic%3D7189195%26sjid%3D2449417013251062800-AP"
                  },
                  "strikethrough": false,
                  "underline": false
                }
              }
            },
            {
              "text_run": {
                "content": ". ",
                "text_element_style": {
                  "bold": false,
                  "inline_code": false,
                  "italic": false,
                  "strikethrough": false,
                  "underline": false
                }
              }
            }
          ],
          "style": {
            "align": 1,
            "folded": false
          }
        }
      },
      {
        "block_id": "F1OtdKdztomsiqxt242cJCVUnce",
        "block_type": 2,
        "parent_id": "QqmGd3jVxowHHjxzps3cH6CLnSc",
        "text": {
          "elements": [
            {
              "text_run": {
                "content": "Similarly, MFA settings for GitHub-linked accounts are managed by GitHub. For more information, see ",
                "text_element_style": {
                  "bold": false,
                  "inline_code": false,
                  "italic": false,
                  "strikethrough": false,
                  "underline": false
                }
              }
            },
            {
              "text_run": {
                "content": "Disabling two-factor authentication for your personal account",
                "text_element_style": {
                  "bold": false,
                  "inline_code": false,
                  "italic": false,
                  "link": {
                    "url": "https%3A%2F%2Fdocs.github.com%2Fen%2Fauthentication%2Fsecuring-your-account-with-two-factor-authentication-2fa%2Fdisabling-two-factor-authentication-for-your-personal-account"
                  },
                  "strikethrough": false,
                  "underline": false
                }
              }
            },
            {
              "text_run": {
                "content": ".",
                "text_element_style": {
                  "bold": false,
                  "inline_code": false,
                  "italic": false,
                  "strikethrough": false,
                  "underline": false
                }
              }
            }
          ],
          "style": {
            "align": 1,
            "folded": false
          }
        }
      },
      {
        "block_id": "QCf5dTsFKoDYqQxQsr9cr0xVnAc",
        "block_type": 2,
        "parent_id": "HE1DdqSMWoslMCx5jiLc9mqTn0g",
        "text": {
          "elements": [
            {
              "text_run": {
                "content": "",
                "text_element_style": {
                  "bold": false,
                  "inline_code": false,
                  "italic": false,
                  "strikethrough": false,
                  "underline": false
                }
              }
            }
          ],
          "style": {
            "align": 1,
            "folded": false
          }
        }
      }
    ],
    "counts": 24
  }
}